adafruit_anchored_group.py
adafruit_circuitpython_anchored_group-1.1.0.dist-info/licenses/LICENSE
adafruit_circuitpython_anchored_group-1.1.0.dist-info/METADATA
adafruit_circuitpython_anchored_group-1.1.0.dist-info/WHEEL
adafruit_circuitpython_anchored_group-1.1.0.dist-info/top_level.txt
adafruit_circuitpython_anchored_group-1.1.0.dist-info/RECORD
