Metadata-Version: 2.4
Name: adafruit-circuitpython-anchored-group
Version: 1.1.0
Summary: A displayio Group that supports placement by anchor_point and anchored_position properties
Author-email: Adafruit Industries <circuitpython@adafruit.com>
License: MIT
Project-URL: Homepage, https://github.com/adafruit/Adafruit_CircuitPython_Anchored_Group
Keywords: adafruit,blinka,circuitpython,micropython,anchored_group,displayio
Classifier: Intended Audience :: Developers
Classifier: Topic :: Software Development :: Libraries
Classifier: Topic :: Software Development :: Embedded Systems
Classifier: Topic :: System :: Hardware
Classifier: License :: OSI Approved :: MIT License
Classifier: Programming Language :: Python :: 3
License-File: LICENSE
Requires-Dist: Adafruit-Blinka
Provides-Extra: optional
Dynamic: license-file
